tesssty/README.rst
tesssty/tesssty/__init__.py
tesssty-0.0.1.dist-info/WHEEL
tesssty-0.0.1.dist-info/METADATA
tesssty-0.0.1.dist-info/RECORD
