Metadata-Version: 2.1
Name: tesssty
Version: 0.0.1
Summary: asd
License: n
Author: Your Name
Author-email: you@example.com
Requires-Python: >=3.10,<4.0
Classifier: License :: Other/Proprietary License
Classifier: Programming Language :: Python :: 3
Classifier: Programming Language :: Python :: 3.10
